{"metrics": {"LINC": {"run_type": "calibrator", "stations": [{"station": "CS002HBA0", "removed": "no", "percentage_flagged": {"initial": 0.6754377424528302, "final": 21.25361933962265}, "percentage_flagged_solutions": {"bandpass": 0.390625, "clock": 0.0, "faraday": 0.0, "polalign": 0.0}}, {"station": "CS002HBA1", "removed": "no", "percentage_flagged": {"initial": 0.7234570504716991, "final": 17.802818349056594}, "percentage_flagged_solutions": {"bandpass": 0.390625, "clock": 0.0, "faraday": 0.0, "polalign": 0.0}}, {"station": "CS003HBA0", "removed": "no", "percentage_flagged": {"initial": 0.8322386122641513, "final": 20.067353066037747}, "percentage_flagged_solutions": {"bandpass": 0.390625, "clock": 0.0, "faraday": 0.0, "polalign": 0.0}}, {"station": "CS003HBA1", "removed": "no", "percentage_flagged": {"initial": 0.6733032051886794, "final": 18.34232839622641}, "percentage_flagged_solutions": {"bandpass": 0.390625, "clock": 0.0, "faraday": 0.0, "polalign": 0.0}}, {"station": "CS004HBA0", "removed": "no", "percentage_flagged": {"initial": 0.6563500646226416, "final": 19.669329433962275}, "percentage_flagged_solutions": {"bandpass": 0.390625, "clock": 0.0, "faraday": 0.0, "polalign": 0.0}}, {"station": "CS004HBA1", "removed": "no", "percentage_flagged": {"initial": 0.662654635849057, "final": 16.97784127358491}, "percentage_flagged_solutions": {"bandpass": 0.390625, "clock": 0.0, "faraday": 0.0, "polalign": 0.0}}, {"station": "CS005HBA0", "removed": "no", "percentage_flagged": {"initial": 0.6395028603773585, "final": 18.0917445283019}, "percentage_flagged_solutions": {"bandpass": 0.390625, "clock": 0.0, "faraday": 0.0, "polalign": 0.0}}, {"station": "CS005HBA1", "removed": "no", "percentage_flagged": {"initial": 0.6459012259433964, "final": 17.457130424528312}, "percentage_flagged_solutions": {"bandpass": 0.390625, "clock": 0.0, "faraday": 0.0, "polalign": 0.0}}, {"station": "CS006HBA0", "removed": "no", "percentage_flagged": {"initial": 0.6560176943396232, "final": 19.01213004716981}, "percentage_flagged_solutions": {"bandpass": 0.390625, "clock": 0.0, "faraday": 0.0, "polalign": 0.0}}, {"station": "CS006HBA1", "removed": "no", "percentage_flagged": {"initial": 0.7547307773584906, "final": 18.572213537735845}, "percentage_flagged_solutions": {"bandpass": 0.390625, "clock": 0.0, "faraday": 0.0, "polalign": 0.0}}, {"station": "CS007HBA0", "removed": "no", "percentage_flagged": {"initial": 0.6576657028301889, "final": 17.663677075471703}, "percentage_flagged_solutions": {"bandpass": 0.390625, "clock": 0.0, "faraday": 0.0, "polalign": 0.0}}, {"station": "CS007HBA1", "removed": "no", "percentage_flagged": {"initial": 0.6955099981132079, "final": 20.383986462264154}, "percentage_flagged_solutions": {"bandpass": 0.390625, "clock": 0.0, "faraday": 0.0, "polalign": 0.0}}, {"station": "CS011HBA0", "removed": "no", "percentage_flagged": {"initial": 0.6517837382075478, "final": 17.40565707547171}, "percentage_flagged_solutions": {"bandpass": 0.390625, "clock": 0.0, "faraday": 0.0, "polalign": 0.0}}, {"station": "CS011HBA1", "removed": "no", "percentage_flagged": {"initial": 0.619292671698113, "final": 19.964164858490566}, "percentage_flagged_solutions": {"bandpass": 0.390625, "clock": 0.0, "faraday": 0.0, "polalign": 0.0}}, {"station": "CS013HBA0", "removed": "no", "percentage_flagged": {"initial": 0.6310575702830189, "final": 19.218250235849045}, "percentage_flagged_solutions": {"bandpass": 0.390625, "clock": 0.0, "faraday": 0.0, "polalign": 0.0}}, {"station": "CS013HBA1", "removed": "no", "percentage_flagged": {"initial": 0.6843280542452831, "final": 20.7121062264151}, "percentage_flagged_solutions": {"bandpass": 0.390625, "clock": 0.0, "faraday": 0.0, "polalign": 0.0}}, {"station": "CS017HBA0", "removed": "no", "percentage_flagged": {"initial": 0.651809936792452, "final": 19.985031933962265}, "percentage_flagged_solutions": {"bandpass": 0.390625, "clock": 0.0, "faraday": 0.0, "polalign": 0.0}}, {"station": "CS017HBA1", "removed": "no", "percentage_flagged": {"initial": 0.6576318683962271, "final": 16.34220297169811}, "percentage_flagged_solutions": {"bandpass": 0.390625, "clock": 0.0, "faraday": 0.0, "polalign": 0.0}}, {"station": "CS021HBA0", "removed": "no", "percentage_flagged": {"initial": 0.6849789915094334, "final": 17.938799575471684}, "percentage_flagged_solutions": {"bandpass": 0.390625, "clock": 0.0, "faraday": 0.0, "polalign": 0.0}}, {"station": "CS021HBA1", "removed": "no", "percentage_flagged": {"initial": 0.6892374415094347, "final": 17.855043584905665}, "percentage_flagged_solutions": {"bandpass": 0.390625, "clock": 0.0, "faraday": 0.0, "polalign": 0.0}}, {"station": "CS024HBA0", "removed": "no", "percentage_flagged": {"initial": 0.9293111287735843, "final": 20.515574905660376}, "percentage_flagged_solutions": {"bandpass": 0.390625, "clock": 0.0, "faraday": 0.0, "polalign": 0.0}}, {"station": "CS024HBA1", "removed": "no", "percentage_flagged": {"initial": 0.9934327306603775, "final": 18.68420773584906}, "percentage_flagged_solutions": {"bandpass": 0.390625, "clock": 0.0, "faraday": 0.0, "polalign": 0.0}}, {"station": "CS026HBA0", "removed": "no", "percentage_flagged": {"initial": 0.8428278415094346, "final": 17.776910566037742}, "percentage_flagged_solutions": {"bandpass": 0.390625, "clock": 0.0, "faraday": 0.0, "polalign": 0.0}}, {"station": "CS026HBA1", "removed": "no", "percentage_flagged": {"initial": 0.8525268844339622, "final": 18.176931273584927}, "percentage_flagged_solutions": {"bandpass": 0.390625, "clock": 0.0, "faraday": 0.0, "polalign": 0.0}}, {"station": "CS028HBA0", "removed": "no", "percentage_flagged": {"initial": 0.8284926405660373, "final": 19.87414679245284}, "percentage_flagged_solutions": {"bandpass": 0.390625, "clock": 0.0, "faraday": 0.0, "polalign": 0.0}}, {"station": "CS028HBA1", "removed": "no", "percentage_flagged": {"initial": 0.8081020495283013, "final": 19.38534438679246}, "percentage_flagged_solutions": {"bandpass": 0.390625, "clock": 0.0, "faraday": 0.0, "polalign": 0.0}}, {"station": "CS030HBA0", "removed": "no", "percentage_flagged": {"initial": 1.0658677877358498, "final": 18.943531792452823}, "percentage_flagged_solutions": {"bandpass": 0.390625, "clock": 0.0, "faraday": 0.0, "polalign": 0.0}}, {"station": "CS030HBA1", "removed": "no", "percentage_flagged": {"initial": 0.9793931330188681, "final": 16.48627726415093}, "percentage_flagged_solutions": {"bandpass": 0.390625, "clock": 0.0, "faraday": 0.0, "polalign": 0.0}}, {"station": "CS031HBA0", "removed": "no", "percentage_flagged": {"initial": 0.8633545396226419, "final": 20.114937877358507}, "percentage_flagged_solutions": {"bandpass": 0.390625, "clock": 0.0, "faraday": 0.0, "polalign": 0.0}}, {"station": "CS031HBA1", "removed": "no", "percentage_flagged": {"initial": 0.8158992811320761, "final": 18.231525424528304}, "percentage_flagged_solutions": {"bandpass": 0.390625, "clock": 0.0, "faraday": 0.0, "polalign": 0.0}}, {"station": "CS101HBA0", "removed": "no", "percentage_flagged": {"initial": 0.7952607216981131, "final": 16.65361457547168}, "percentage_flagged_solutions": {"bandpass": 0.390625, "clock": 0.0, "faraday": 0.0, "polalign": 0.0}}, {"station": "CS101HBA1", "removed": "no", "percentage_flagged": {"initial": 0.7805531396226421, "final": 22.884485849056592}, "percentage_flagged_solutions": {"bandpass": 0.390625, "clock": 0.0, "faraday": 0.0, "polalign": 0.0}}, {"station": "CS103HBA0", "removed": "no", "percentage_flagged": {"initial": 0.8981403386792455, "final": 14.836814292452827}, "percentage_flagged_solutions": {"bandpass": 0.390625, "clock": 0.0, "faraday": 0.0, "polalign": 0.0}}, {"station": "CS103HBA1", "removed": "no", "percentage_flagged": {"initial": 0.8093626377358489, "final": 16.686264952830175}, "percentage_flagged_solutions": {"bandpass": 0.390625, "clock": 0.0, "faraday": 0.0, "polalign": 0.0}}, {"station": "CS201HBA0", "removed": "no", "percentage_flagged": {"initial": 0.8923189419811325, "final": 20.224113301886796}, "percentage_flagged_solutions": {"bandpass": 0.390625, "clock": 0.0, "faraday": 0.0, "polalign": 0.0}}, {"station": "CS201HBA1", "removed": "no", "percentage_flagged": {"initial": 0.8301030679245283, "final": 19.42340537735849}, "percentage_flagged_solutions": {"bandpass": 0.390625, "clock": 0.0, "faraday": 0.0, "polalign": 0.0}}, {"station": "CS301HBA0", "removed": "no", "percentage_flagged": {"initial": 0.9645313165094347, "final": 19.524168915094346}, "percentage_flagged_solutions": {"bandpass": 0.390625, "clock": 0.0, "faraday": 0.0, "polalign": 0.0}}, {"station": "CS301HBA1", "removed": "no", "percentage_flagged": {"initial": 0.9450696665094342, "final": 16.77905735849057}, "percentage_flagged_solutions": {"bandpass": 0.390625, "clock": 0.0, "faraday": 0.0, "polalign": 0.0}}, {"station": "CS302HBA0", "removed": "no", "percentage_flagged": {"initial": 1.0695111877358485, "final": 17.629135330188685}, "percentage_flagged_solutions": {"bandpass": 0.390625, "clock": 0.0, "faraday": 0.0, "polalign": 0.0}}, {"station": "CS302HBA1", "removed": "no", "percentage_flagged": {"initial": 0.9275642047169821, "final": 18.015947971698125}, "percentage_flagged_solutions": {"bandpass": 0.390625, "clock": 0.0, "faraday": 0.0, "polalign": 0.0}}, {"station": "CS401HBA0", "removed": "no", "percentage_flagged": {"initial": 0.8684677952830188, "final": 19.019911462264147}, "percentage_flagged_solutions": {"bandpass": 0.390625, "clock": 0.0, "faraday": 0.0, "polalign": 0.0}}, {"station": "CS401HBA1", "removed": "no", "percentage_flagged": {"initial": 0.8603364136792453, "final": 16.347190141509444}, "percentage_flagged_solutions": {"bandpass": 0.390625, "clock": 0.0, "faraday": 0.0, "polalign": 0.0}}, {"station": "CS501HBA0", "removed": "no", "percentage_flagged": {"initial": 0.8617942707547174, "final": 15.948485377358487}, "percentage_flagged_solutions": {"bandpass": 0.390625, "clock": 0.0, "faraday": 0.0, "polalign": 0.0}}, {"station": "CS501HBA1", "removed": "no", "percentage_flagged": {"initial": 0.9150999660377359, "final": 17.601988726415087}, "percentage_flagged_solutions": {"bandpass": 0.390625, "clock": 0.0, "faraday": 0.0, "polalign": 0.0}}, {"station": "DE602HBA", "removed": "no", "percentage_flagged": {"initial": 0.8071986358490568, "final": 9.46709391509434}, "percentage_flagged_solutions": {"bandpass": 0.390625, "clock": 0.0, "faraday": 0.0, "polalign": 0.0}}, {"station": "DE603HBA", "removed": "no", "percentage_flagged": {"initial": 0.49273166603773555, "final": 10.760097971698116}, "percentage_flagged_solutions": {"bandpass": 0.390625, "clock": 0.0, "faraday": 0.0, "polalign": 0.0}}, {"station": "DE604HBA", "removed": "no", "percentage_flagged": {"initial": 1.0630626537735843, "final": 16.073358773584893}, "percentage_flagged_solutions": {"bandpass": 0.390625, "clock": 0.0, "faraday": 0.0, "polalign": 0.0}}, {"station": "DE605HBA", "removed": "no", "percentage_flagged": {"initial": 0.9775969419811326, "final": 23.94323834905661}, "percentage_flagged_solutions": {"bandpass": 0.390625, "clock": 0.0, "faraday": 0.0, "polalign": 0.0}}, {"station": "DE609HBA", "removed": "no", "percentage_flagged": {"initial": 1.0928217155660358, "final": 21.958614245283027}, "percentage_flagged_solutions": {"bandpass": 0.390625, "clock": 0.0, "faraday": 0.0, "polalign": 0.0}}, {"station": "FR606HBA", "removed": "no", "percentage_flagged": {"initial": 0.5786075514150949, "final": 9.805378443396224}, "percentage_flagged_solutions": {"bandpass": 0.390625, "clock": 0.0, "faraday": 0.0, "polalign": 0.0}}, {"station": "IE613HBA", "removed": "no", "percentage_flagged": {"initial": 0.4042163235849055, "final": 7.493609622641506}, "percentage_flagged_solutions": {"bandpass": 0.390625, "clock": 0.0, "faraday": 0.0, "polalign": 0.0}}, {"station": "LV614HBA", "removed": "no", "percentage_flagged": {"initial": 0.39292961273584903, "final": 100.0}, "percentage_flagged_solutions": {"bandpass": 100.0, "clock": 100.0, "faraday": 90.667724609375, "polalign": 0.0}}, {"station": "PL610HBA", "removed": "no", "percentage_flagged": {"initial": 0.4487094136792451, "final": 100.0}, "percentage_flagged_solutions": {"bandpass": 100.0, "clock": 100.0, "faraday": 100.0, "polalign": 0.0}}, {"station": "PL611HBA", "removed": "no", "percentage_flagged": {"initial": 0.5093670603773585, "final": 22.59375518867923}, "percentage_flagged_solutions": {"bandpass": 0.390625, "clock": 100.0, "faraday": 17.333984375, "polalign": 0.0}}, {"station": "PL612HBA", "removed": "no", "percentage_flagged": {"initial": 0.39189710094339625, "final": 100.0}, "percentage_flagged_solutions": {"bandpass": 100.0, "clock": 100.0, "faraday": 87.3291015625, "polalign": 0.0}}, {"station": "RS106HBA", "removed": "no", "percentage_flagged": {"initial": 0.7860923820754719, "final": 17.982827075471704}, "percentage_flagged_solutions": {"bandpass": 0.390625, "clock": 0.0, "faraday": 0.0, "polalign": 0.0}}, {"station": "RS205HBA", "removed": "no", "percentage_flagged": {"initial": 0.8148175311320752, "final": 15.953898679245274}, "percentage_flagged_solutions": {"bandpass": 0.390625, "clock": 0.0, "faraday": 0.0, "polalign": 0.0}}, {"station": "RS208HBA", "removed": "no", "percentage_flagged": {"initial": 0.8980132985849055, "final": 30.09503514150943}, "percentage_flagged_solutions": {"bandpass": 0.390625, "clock": 0.0, "faraday": 0.0, "polalign": 0.0}}, {"station": "RS210HBA", "removed": "no", "percentage_flagged": {"initial": 0.6968219429245287, "final": 9.702975613207556}, "percentage_flagged_solutions": {"bandpass": 0.390625, "clock": 0.0, "faraday": 0.0, "polalign": 0.0}}, {"station": "RS305HBA", "removed": "no", "percentage_flagged": {"initial": 0.9556041938679247, "final": 13.340532358490567}, "percentage_flagged_solutions": {"bandpass": 0.390625, "clock": 0.0, "faraday": 0.0, "polalign": 0.0}}, {"station": "RS306HBA", "removed": "no", "percentage_flagged": {"initial": 1.04385618726415, "final": 9.375460471698114}, "percentage_flagged_solutions": {"bandpass": 0.390625, "clock": 0.0, "faraday": 0.0, "polalign": 0.0}}, {"station": "RS307HBA", "removed": "no", "percentage_flagged": {"initial": 0.7645803485849058, "final": 11.966590094339628}, "percentage_flagged_solutions": {"bandpass": 0.390625, "clock": 0.0, "faraday": 0.0, "polalign": 0.0}}, {"station": "RS310HBA", "removed": "no", "percentage_flagged": {"initial": 0.7632467216981137, "final": 10.082390660377364}, "percentage_flagged_solutions": {"bandpass": 0.390625, "clock": 0.0, "faraday": 0.0, "polalign": 0.0}}, {"station": "RS406HBA", "removed": "no", "percentage_flagged": {"initial": 0.5961283537735854, "final": 14.547024481132077}, "percentage_flagged_solutions": {"bandpass": 0.390625, "clock": 0.0, "faraday": 0.0, "polalign": 0.0}}, {"station": "RS407HBA", "removed": "no", "percentage_flagged": {"initial": 0.6199601943396237, "final": 15.513613820754706}, "percentage_flagged_solutions": {"bandpass": 0.390625, "clock": 0.0, "faraday": 0.0, "polalign": 0.0}}, {"station": "RS409HBA", "removed": "no", "percentage_flagged": {"initial": 0.5838316367924529, "final": 14.85894966981132}, "percentage_flagged_solutions": {"bandpass": 0.390625, "clock": 0.0, "faraday": 0.0, "polalign": 0.0}}, {"station": "RS503HBA", "removed": "no", "percentage_flagged": {"initial": 0.7904265561320752, "final": 10.017454669811325}, "percentage_flagged_solutions": {"bandpass": 0.390625, "clock": 0.0, "faraday": 0.0, "polalign": 0.0}}, {"station": "RS508HBA", "removed": "no", "percentage_flagged": {"initial": 0.6129438844339615, "final": 9.703559764150944}, "percentage_flagged_solutions": {"bandpass": 0.390625, "clock": 0.0, "faraday": 0.0, "polalign": 0.0}}, {"station": "RS509HBA", "removed": "no", "percentage_flagged": {"initial": 0.6074055952830186, "final": 26.07450613207546}, "percentage_flagged_solutions": {"bandpass": 0.390625, "clock": 0.0, "faraday": 0.0, "polalign": 0.0}}, {"station": "SE607HBA", "removed": "no", "percentage_flagged": {"initial": 0.4016621174528302, "final": 10.650528773584913}, "percentage_flagged_solutions": {"bandpass": 0.390625, "clock": 0.0, "faraday": 0.0, "polalign": 0.0}}, {"station": "UK608HBA", "removed": "no", "percentage_flagged": {"initial": 1.2490303882075466, "final": 9.515095283018873}, "percentage_flagged_solutions": {"bandpass": 0.390625, "clock": 0.0, "faraday": 0.0, "polalign": 0.0}}], "field_name": "POINT", "filtered_baselines_by_user": "*&", "close_sources": []}}}