{"metrics": {"LINC": {"run_type": "calibrator", "stations": [{"station": "CS002HBA0", "removed": "no", "percentage_flagged": {"initial": 5.835453852813854, "final": 26.815526406926416}, "percentage_flagged_solutions": {"bandpass": 0.390625, "clock": 0.0, "faraday": 0.0, "polalign": 0.0}}, {"station": "CS002HBA1", "removed": "no", "percentage_flagged": {"initial": 5.539334329004329, "final": 20.299731168831162}, "percentage_flagged_solutions": {"bandpass": 0.390625, "clock": 0.0, "faraday": 0.0, "polalign": 0.0}}, {"station": "CS003HBA0", "removed": "no", "percentage_flagged": {"initial": 5.464805584415591, "final": 18.57526536796536}, "percentage_flagged_solutions": {"bandpass": 0.390625, "clock": 0.0, "faraday": 0.0, "polalign": 0.0}}, {"station": "CS003HBA1", "removed": "no", "percentage_flagged": {"initial": 5.746380216450218, "final": 25.362782683982697}, "percentage_flagged_solutions": {"bandpass": 0.390625, "clock": 0.0, "faraday": 0.0, "polalign": 0.0}}, {"station": "CS004HBA0", "removed": "no", "percentage_flagged": {"initial": 5.573705627705626, "final": 23.140038961038943}, "percentage_flagged_solutions": {"bandpass": 0.390625, "clock": 0.0, "faraday": 0.0, "polalign": 0.0}}, {"station": "CS004HBA1", "removed": "no", "percentage_flagged": {"initial": 5.511042337662338, "final": 20.399210389610385}, "percentage_flagged_solutions": {"bandpass": 0.390625, "clock": 0.0, "faraday": 0.0, "polalign": 0.0}}, {"station": "CS005HBA0", "removed": "no", "percentage_flagged": {"initial": 5.510596969696965, "final": 19.982290476190467}, "percentage_flagged_solutions": {"bandpass": 0.390625, "clock": 0.0, "faraday": 0.0, "polalign": 0.0}}, {"station": "CS005HBA1", "removed": "no", "percentage_flagged": {"initial": 5.550556363636368, "final": 21.004431168831164}, "percentage_flagged_solutions": {"bandpass": 0.390625, "clock": 0.0, "faraday": 0.0, "polalign": 0.0}}, {"station": "CS006HBA0", "removed": "no", "percentage_flagged": {"initial": 5.483521168831168, "final": 17.950247619047634}, "percentage_flagged_solutions": {"bandpass": 0.390625, "clock": 0.0, "faraday": 0.0, "polalign": 0.0}}, {"station": "CS006HBA1", "removed": "no", "percentage_flagged": {"initial": 5.80114411255411, "final": 23.966393939393935}, "percentage_flagged_solutions": {"bandpass": 0.390625, "clock": 0.0, "faraday": 0.0, "polalign": 0.0}}, {"station": "CS007HBA0", "removed": "no", "percentage_flagged": {"initial": 5.480619610389611, "final": 19.54275194805194}, "percentage_flagged_solutions": {"bandpass": 0.390625, "clock": 0.0, "faraday": 0.0, "polalign": 0.0}}, {"station": "CS007HBA1", "removed": "no", "percentage_flagged": {"initial": 5.534598658008657, "final": 22.18775411255411}, "percentage_flagged_solutions": {"bandpass": 0.390625, "clock": 0.0, "faraday": 0.0, "polalign": 0.0}}, {"station": "CS011HBA0", "removed": "no", "percentage_flagged": {"initial": 5.6863405627705665, "final": 23.515271861471852}, "percentage_flagged_solutions": {"bandpass": 0.390625, "clock": 0.0, "faraday": 0.0, "polalign": 0.0}}, {"station": "CS011HBA1", "removed": "no", "percentage_flagged": {"initial": 5.699895108225105, "final": 23.800023376623365}, "percentage_flagged_solutions": {"bandpass": 0.390625, "clock": 0.0, "faraday": 0.0, "polalign": 0.0}}, {"station": "CS013HBA0", "removed": "no", "percentage_flagged": {"initial": 5.613606536796538, "final": 25.40446536796537}, "percentage_flagged_solutions": {"bandpass": 0.390625, "clock": 0.0, "faraday": 0.0, "polalign": 0.0}}, {"station": "CS013HBA1", "removed": "no", "percentage_flagged": {"initial": 5.580568874458874, "final": 23.774093506493514}, "percentage_flagged_solutions": {"bandpass": 0.390625, "clock": 0.0, "faraday": 0.0, "polalign": 0.0}}, {"station": "CS017HBA0", "removed": "no", "percentage_flagged": {"initial": 5.501292380952381, "final": 20.403711861471855}, "percentage_flagged_solutions": {"bandpass": 0.390625, "clock": 0.0, "faraday": 0.0, "polalign": 0.0}}, {"station": "CS017HBA1", "removed": "no", "percentage_flagged": {"initial": 5.469755281385278, "final": 17.789168398268398}, "percentage_flagged_solutions": {"bandpass": 0.390625, "clock": 0.0, "faraday": 0.0, "polalign": 0.0}}, {"station": "CS024HBA0", "removed": "no", "percentage_flagged": {"initial": 5.6385969696969696, "final": 20.441694242424234}, "percentage_flagged_solutions": {"bandpass": 0.390625, "clock": 0.0, "faraday": 0.0, "polalign": 0.0}}, {"station": "CS024HBA1", "removed": "no", "percentage_flagged": {"initial": 5.649095324675324, "final": 19.739479956709953}, "percentage_flagged_solutions": {"bandpass": 0.390625, "clock": 0.0, "faraday": 0.0, "polalign": 0.0}}, {"station": "CS026HBA0", "removed": "no", "percentage_flagged": {"initial": 5.816809220779227, "final": 23.780019480519492}, "percentage_flagged_solutions": {"bandpass": 0.390625, "clock": 0.0, "faraday": 0.0, "polalign": 0.0}}, {"station": "CS026HBA1", "removed": "no", "percentage_flagged": {"initial": 5.755177316017317, "final": 21.438738528138526}, "percentage_flagged_solutions": {"bandpass": 0.390625, "clock": 0.0, "faraday": 0.0, "polalign": 0.0}}, {"station": "CS028HBA0", "removed": "no", "percentage_flagged": {"initial": 5.595962900432901, "final": 19.166721731601726}, "percentage_flagged_solutions": {"bandpass": 0.390625, "clock": 0.0, "faraday": 0.0, "polalign": 0.0}}, {"station": "CS028HBA1", "removed": "no", "percentage_flagged": {"initial": 5.588896406926402, "final": 19.70083974025974}, "percentage_flagged_solutions": {"bandpass": 0.390625, "clock": 0.0, "faraday": 0.0, "polalign": 0.0}}, {"station": "CS030HBA0", "removed": "no", "percentage_flagged": {"initial": 5.638133593073591, "final": 18.51255164502166}, "percentage_flagged_solutions": {"bandpass": 0.390625, "clock": 0.0, "faraday": 0.0, "polalign": 0.0}}, {"station": "CS030HBA1", "removed": "no", "percentage_flagged": {"initial": 5.574256709956702, "final": 17.397263809523825}, "percentage_flagged_solutions": {"bandpass": 0.390625, "clock": 0.0, "faraday": 0.0, "polalign": 0.0}}, {"station": "CS031HBA0", "removed": "no", "percentage_flagged": {"initial": 100.0, "final": 100.0}, "percentage_flagged_solutions": {"bandpass": 100.0, "clock": 100.0, "faraday": 0.0, "polalign": 0.0}}, {"station": "CS031HBA1", "removed": "no", "percentage_flagged": {"initial": 100.0, "final": 100.0}, "percentage_flagged_solutions": {"bandpass": 100.0, "clock": 100.0, "faraday": 0.0, "polalign": 0.0}}, {"station": "CS101HBA0", "removed": "no", "percentage_flagged": {"initial": 5.660328441558441, "final": 21.172166233766244}, "percentage_flagged_solutions": {"bandpass": 0.390625, "clock": 0.0, "faraday": 0.0, "polalign": 0.0}}, {"station": "CS101HBA1", "removed": "no", "percentage_flagged": {"initial": 5.616695757575756, "final": 21.529766666666657}, "percentage_flagged_solutions": {"bandpass": 0.390625, "clock": 0.0, "faraday": 0.0, "polalign": 0.0}}, {"station": "CS103HBA0", "removed": "no", "percentage_flagged": {"initial": 5.9242243290043275, "final": 21.5298329004329}, "percentage_flagged_solutions": {"bandpass": 0.390625, "clock": 0.0, "faraday": 0.0, "polalign": 0.0}}, {"station": "CS103HBA1", "removed": "no", "percentage_flagged": {"initial": 5.671236883116881, "final": 19.652411688311677}, "percentage_flagged_solutions": {"bandpass": 0.390625, "clock": 0.0, "faraday": 0.0, "polalign": 0.0}}, {"station": "CS201HBA0", "removed": "no", "percentage_flagged": {"initial": 5.938351298701297, "final": 23.595845887445886}, "percentage_flagged_solutions": {"bandpass": 0.390625, "clock": 0.0, "faraday": 0.0, "polalign": 0.0}}, {"station": "CS201HBA1", "removed": "no", "percentage_flagged": {"initial": 5.592684805194804, "final": 19.23308787878789}, "percentage_flagged_solutions": {"bandpass": 0.390625, "clock": 0.0, "faraday": 0.0, "polalign": 0.0}}, {"station": "CS301HBA0", "removed": "no", "percentage_flagged": {"initial": 5.641562987012986, "final": 18.66724264069265}, "percentage_flagged_solutions": {"bandpass": 0.390625, "clock": 0.0, "faraday": 0.0, "polalign": 0.0}}, {"station": "CS301HBA1", "removed": "no", "percentage_flagged": {"initial": 5.63850883116883, "final": 18.418785887445893}, "percentage_flagged_solutions": {"bandpass": 0.390625, "clock": 0.0, "faraday": 0.0, "polalign": 0.0}}, {"station": "CS302HBA0", "removed": "no", "percentage_flagged": {"initial": 5.638360952380951, "final": 15.346765714285715}, "percentage_flagged_solutions": {"bandpass": 0.390625, "clock": 0.0, "faraday": 0.0, "polalign": 0.0}}, {"station": "CS302HBA1", "removed": "no", "percentage_flagged": {"initial": 5.602440692640693, "final": 16.90718913419915}, "percentage_flagged_solutions": {"bandpass": 0.390625, "clock": 0.0, "faraday": 0.0, "polalign": 0.0}}, {"station": "CS401HBA0", "removed": "no", "percentage_flagged": {"initial": 5.749125151515151, "final": 22.714178354978333}, "percentage_flagged_solutions": {"bandpass": 0.390625, "clock": 0.0, "faraday": 0.0, "polalign": 0.0}}, {"station": "CS401HBA1", "removed": "no", "percentage_flagged": {"initial": 5.633404632034629, "final": 18.729317402597395}, "percentage_flagged_solutions": {"bandpass": 0.390625, "clock": 0.0, "faraday": 0.0, "polalign": 0.0}}, {"station": "CS501HBA0", "removed": "no", "percentage_flagged": {"initial": 5.6562976623376615, "final": 19.597829004328997}, "percentage_flagged_solutions": {"bandpass": 0.390625, "clock": 0.0, "faraday": 0.0, "polalign": 0.0}}, {"station": "CS501HBA1", "removed": "no", "percentage_flagged": {"initial": 5.652653073593076, "final": 18.976211125541123}, "percentage_flagged_solutions": {"bandpass": 0.390625, "clock": 0.0, "faraday": 0.0, "polalign": 0.0}}, {"station": "DE602HBA", "removed": "no", "percentage_flagged": {"initial": 35.0433645021645, "final": 40.803780519480505}, "percentage_flagged_solutions": {"bandpass": 0.390625, "clock": 0.0, "faraday": 0.0, "polalign": 0.0}}, {"station": "DE603HBA", "removed": "no", "percentage_flagged": {"initial": 6.1214958441558425, "final": 13.946577099567097}, "percentage_flagged_solutions": {"bandpass": 0.390625, "clock": 0.0, "faraday": 0.0, "polalign": 0.0}}, {"station": "DE604HBA", "removed": "no", "percentage_flagged": {"initial": 7.842394935064934, "final": 12.80479896103896}, "percentage_flagged_solutions": {"bandpass": 0.390625, "clock": 0.0, "faraday": 0.0, "polalign": 0.0}}, {"station": "DE605HBA", "removed": "no", "percentage_flagged": {"initial": 5.716044675324675, "final": 20.313483549783555}, "percentage_flagged_solutions": {"bandpass": 0.390625, "clock": 0.0, "faraday": 0.0, "polalign": 0.0}}, {"station": "DE609HBA", "removed": "no", "percentage_flagged": {"initial": 6.071153506493509, "final": 15.896222467532475}, "percentage_flagged_solutions": {"bandpass": 0.390625, "clock": 0.0, "faraday": 0.0, "polalign": 0.0}}, {"station": "FR606HBA", "removed": "no", "percentage_flagged": {"initial": 5.682906190476187, "final": 100.0}, "percentage_flagged_solutions": {"bandpass": 100.0, "clock": 100.0, "faraday": 100.0, "polalign": 0.0}}, {"station": "IE613HBA", "removed": "no", "percentage_flagged": {"initial": 5.3324424675324655, "final": 8.698632121212125}, "percentage_flagged_solutions": {"bandpass": 0.390625, "clock": 0.0, "faraday": 0.68359375, "polalign": 0.0}}, {"station": "LV614HBA", "removed": "no", "percentage_flagged": {"initial": 5.278399004329006, "final": 9.850363463203465}, "percentage_flagged_solutions": {"bandpass": 0.390625, "clock": 0.0, "faraday": 0.0, "polalign": 0.0}}, {"station": "PL610HBA", "removed": "no", "percentage_flagged": {"initial": 5.36639948051948, "final": 10.848321688311689}, "percentage_flagged_solutions": {"bandpass": 0.390625, "clock": 0.0, "faraday": 0.0, "polalign": 0.0}}, {"station": "PL611HBA", "removed": "no", "percentage_flagged": {"initial": 5.595017186147184, "final": 9.421445064935067}, "percentage_flagged_solutions": {"bandpass": 0.390625, "clock": 0.0, "faraday": 0.0, "polalign": 0.0}}, {"station": "PL612HBA", "removed": "no", "percentage_flagged": {"initial": 5.269291515151518, "final": 10.422678831168826}, "percentage_flagged_solutions": {"bandpass": 0.390625, "clock": 0.0, "faraday": 0.0, "polalign": 0.0}}, {"station": "RS106HBA", "removed": "no", "percentage_flagged": {"initial": 5.580771948051946, "final": 14.98306770562771}, "percentage_flagged_solutions": {"bandpass": 0.390625, "clock": 0.0, "faraday": 0.0, "polalign": 0.0}}, {"station": "RS205HBA", "removed": "no", "percentage_flagged": {"initial": 5.53958147186147, "final": 12.394803679653675}, "percentage_flagged_solutions": {"bandpass": 0.390625, "clock": 0.0, "faraday": 0.0, "polalign": 0.0}}, {"station": "RS208HBA", "removed": "no", "percentage_flagged": {"initial": 5.57683974025974, "final": 13.724757878787877}, "percentage_flagged_solutions": {"bandpass": 0.390625, "clock": 0.0, "faraday": 0.0, "polalign": 0.0}}, {"station": "RS210HBA", "removed": "no", "percentage_flagged": {"initial": 5.561491255411251, "final": 10.424876969696964}, "percentage_flagged_solutions": {"bandpass": 0.390625, "clock": 0.0, "faraday": 0.0, "polalign": 0.0}}, {"station": "RS305HBA", "removed": "no", "percentage_flagged": {"initial": 5.9738570129870165, "final": 14.678123463203468}, "percentage_flagged_solutions": {"bandpass": 0.390625, "clock": 0.0, "faraday": 0.0, "polalign": 0.0}}, {"station": "RS306HBA", "removed": "no", "percentage_flagged": {"initial": 5.498464025974026, "final": 22.432079956709952}, "percentage_flagged_solutions": {"bandpass": 13.037109375, "clock": 0.0, "faraday": 0.0, "polalign": 0.0}}, {"station": "RS310HBA", "removed": "no", "percentage_flagged": {"initial": 5.518174805194804, "final": 10.885663939393938}, "percentage_flagged_solutions": {"bandpass": 0.390625, "clock": 0.0, "faraday": 0.0, "polalign": 0.0}}, {"station": "RS406HBA", "removed": "no", "percentage_flagged": {"initial": 5.545148874458873, "final": 12.04548813852814}, "percentage_flagged_solutions": {"bandpass": 0.390625, "clock": 0.0, "faraday": 0.0, "polalign": 0.0}}, {"station": "RS409HBA", "removed": "no", "percentage_flagged": {"initial": 5.4931897835497825, "final": 17.122513809523802}, "percentage_flagged_solutions": {"bandpass": 0.830078125, "clock": 0.0, "faraday": 0.0, "polalign": 0.0}}, {"station": "RS503HBA", "removed": "no", "percentage_flagged": {"initial": 5.513757012987017, "final": 12.30892333333334}, "percentage_flagged_solutions": {"bandpass": 0.390625, "clock": 0.0, "faraday": 0.0, "polalign": 0.0}}, {"station": "RS508HBA", "removed": "no", "percentage_flagged": {"initial": 5.493135151515148, "final": 12.348988095238099}, "percentage_flagged_solutions": {"bandpass": 0.390625, "clock": 0.0, "faraday": 0.0, "polalign": 0.0}}, {"station": "RS509HBA", "removed": "no", "percentage_flagged": {"initial": 5.523391428571432, "final": 10.074644025974013}, "percentage_flagged_solutions": {"bandpass": 0.390625, "clock": 0.0, "faraday": 0.0, "polalign": 0.0}}, {"station": "SE607HBA", "removed": "no", "percentage_flagged": {"initial": 5.473854329004327, "final": 10.732596233766238}, "percentage_flagged_solutions": {"bandpass": 0.390625, "clock": 0.0, "faraday": 0.0, "polalign": 0.0}}, {"station": "UK608HBA", "removed": "no", "percentage_flagged": {"initial": 100.0, "final": 100.0}, "percentage_flagged_solutions": {"bandpass": 100.0, "clock": 100.0, "faraday": 0.0, "polalign": 0.0}}], "field_name": "3c295", "filtered_baselines_by_user": "*&", "close_sources": []}}}