{"metrics": {"LINC": {"run_type": "calibrator", "stations": [{"station": "CS001HBA0", "removed": "no", "percentage_flagged": {"initial": 1.0404840744588757, "final": 13.860512683982678}, "percentage_flagged_solutions": {"bandpass": 0.390625, "clock": 0.0, "faraday": 0.0, "polalign": 0.0}}, {"station": "CS001HBA1", "removed": "no", "percentage_flagged": {"initial": 1.020054785714286, "final": 15.412139480519482}, "percentage_flagged_solutions": {"bandpass": 0.390625, "clock": 0.0, "faraday": 0.0, "polalign": 0.0}}, {"station": "CS002HBA0", "removed": "no", "percentage_flagged": {"initial": 1.123522282683983, "final": 21.405395584415597}, "percentage_flagged_solutions": {"bandpass": 0.390625, "clock": 0.0, "faraday": 0.0, "polalign": 0.0}}, {"station": "CS002HBA1", "removed": "no", "percentage_flagged": {"initial": 1.080158671861472, "final": 34.35935766233765}, "percentage_flagged_solutions": {"bandpass": 14.306640625, "clock": 0.0, "faraday": 0.0, "polalign": 0.0}}, {"station": "CS003HBA0", "removed": "no", "percentage_flagged": {"initial": 1.0702855073593087, "final": 18.62898887445887}, "percentage_flagged_solutions": {"bandpass": 0.390625, "clock": 0.0, "faraday": 0.0, "polalign": 0.0}}, {"station": "CS003HBA1", "removed": "no", "percentage_flagged": {"initial": 1.1297161255411265, "final": 22.269700259740265}, "percentage_flagged_solutions": {"bandpass": 0.390625, "clock": 0.0, "faraday": 0.0, "polalign": 0.0}}, {"station": "CS004HBA0", "removed": "no", "percentage_flagged": {"initial": 1.055484717316017, "final": 17.632878051948058}, "percentage_flagged_solutions": {"bandpass": 0.390625, "clock": 0.0, "faraday": 0.0, "polalign": 0.0}}, {"station": "CS004HBA1", "removed": "no", "percentage_flagged": {"initial": 1.1875825813852823, "final": 19.782637056277057}, "percentage_flagged_solutions": {"bandpass": 0.390625, "clock": 0.0, "faraday": 0.0, "polalign": 0.0}}, {"station": "CS005HBA0", "removed": "no", "percentage_flagged": {"initial": 1.0624459294372293, "final": 13.985390822510821}, "percentage_flagged_solutions": {"bandpass": 0.390625, "clock": 0.0, "faraday": 0.0, "polalign": 0.0}}, {"station": "CS005HBA1", "removed": "no", "percentage_flagged": {"initial": 1.0812156095238106, "final": 23.999738528138522}, "percentage_flagged_solutions": {"bandpass": 0.390625, "clock": 0.0, "faraday": 0.0, "polalign": 0.0}}, {"station": "CS006HBA0", "removed": "no", "percentage_flagged": {"initial": 1.061288982251082, "final": 22.707113333333336}, "percentage_flagged_solutions": {"bandpass": 7.763671875, "clock": 0.0, "faraday": 0.0, "polalign": 0.0}}, {"station": "CS006HBA1", "removed": "no", "percentage_flagged": {"initial": 1.1454767627705624, "final": 22.03681653679654}, "percentage_flagged_solutions": {"bandpass": 0.390625, "clock": 0.0, "faraday": 0.0, "polalign": 0.0}}, {"station": "CS007HBA0", "removed": "no", "percentage_flagged": {"initial": 1.1064943290043285, "final": 30.600378528138528}, "percentage_flagged_solutions": {"bandpass": 15.72265625, "clock": 0.0, "faraday": 0.0, "polalign": 0.0}}, {"station": "CS007HBA1", "removed": "no", "percentage_flagged": {"initial": 1.0909759212121206, "final": 17.071805584415582}, "percentage_flagged_solutions": {"bandpass": 0.390625, "clock": 0.0, "faraday": 0.0, "polalign": 0.0}}, {"station": "CS011HBA0", "removed": "no", "percentage_flagged": {"initial": 1.0249894619047626, "final": 35.02652303030303}, "percentage_flagged_solutions": {"bandpass": 11.23046875, "clock": 0.0, "faraday": 0.0, "polalign": 0.0}}, {"station": "CS011HBA1", "removed": "no", "percentage_flagged": {"initial": 1.0384249190476198, "final": 14.67176658008658}, "percentage_flagged_solutions": {"bandpass": 0.390625, "clock": 0.0, "faraday": 0.0, "polalign": 0.0}}, {"station": "CS013HBA0", "removed": "no", "percentage_flagged": {"initial": 1.1250214896103898, "final": 23.96836363636362}, "percentage_flagged_solutions": {"bandpass": 0.390625, "clock": 0.0, "faraday": 0.0, "polalign": 0.0}}, {"station": "CS013HBA1", "removed": "no", "percentage_flagged": {"initial": 1.13371075021645, "final": 25.880289826839835}, "percentage_flagged_solutions": {"bandpass": 0.390625, "clock": 0.0, "faraday": 0.0, "polalign": 0.0}}, {"station": "CS017HBA0", "removed": "no", "percentage_flagged": {"initial": 1.0085852038961043, "final": 13.861623160173158}, "percentage_flagged_solutions": {"bandpass": 0.390625, "clock": 0.0, "faraday": 0.0, "polalign": 0.0}}, {"station": "CS017HBA1", "removed": "no", "percentage_flagged": {"initial": 1.0186412779220781, "final": 13.833584069264074}, "percentage_flagged_solutions": {"bandpass": 0.390625, "clock": 0.0, "faraday": 0.0, "polalign": 0.0}}, {"station": "CS021HBA0", "removed": "no", "percentage_flagged": {"initial": 1.071056738095238, "final": 16.5141312987013}, "percentage_flagged_solutions": {"bandpass": 0.390625, "clock": 0.0, "faraday": 0.0, "polalign": 0.0}}, {"station": "CS021HBA1", "removed": "no", "percentage_flagged": {"initial": 1.0830572363636362, "final": 15.14462060606061}, "percentage_flagged_solutions": {"bandpass": 0.390625, "clock": 0.0, "faraday": 0.0, "polalign": 0.0}}, {"station": "CS024HBA0", "removed": "no", "percentage_flagged": {"initial": 1.3785500601731604, "final": 13.950987532467533}, "percentage_flagged_solutions": {"bandpass": 0.390625, "clock": 0.0, "faraday": 0.0, "polalign": 0.0}}, {"station": "CS024HBA1", "removed": "no", "percentage_flagged": {"initial": 8.602851774891779, "final": 23.940736839826837}, "percentage_flagged_solutions": {"bandpass": 3.662109375, "clock": 0.0, "faraday": 0.0, "polalign": 0.0}}, {"station": "CS026HBA0", "removed": "no", "percentage_flagged": {"initial": 1.5571300770562764, "final": 14.624490259740261}, "percentage_flagged_solutions": {"bandpass": 0.390625, "clock": 0.0, "faraday": 0.0, "polalign": 0.0}}, {"station": "CS026HBA1", "removed": "no", "percentage_flagged": {"initial": 1.53656468008658, "final": 15.571859956709947}, "percentage_flagged_solutions": {"bandpass": 0.390625, "clock": 0.0, "faraday": 0.0, "polalign": 0.0}}, {"station": "CS028HBA0", "removed": "no", "percentage_flagged": {"initial": 1.4795250861471858, "final": 12.547560389610387}, "percentage_flagged_solutions": {"bandpass": 0.390625, "clock": 0.0, "faraday": 0.0, "polalign": 0.0}}, {"station": "CS028HBA1", "removed": "no", "percentage_flagged": {"initial": 1.4924719103896105, "final": 12.346739740259734}, "percentage_flagged_solutions": {"bandpass": 0.390625, "clock": 0.0, "faraday": 0.0, "polalign": 0.0}}, {"station": "CS030HBA0", "removed": "no", "percentage_flagged": {"initial": 1.4674758142857152, "final": 15.312591861471873}, "percentage_flagged_solutions": {"bandpass": 0.390625, "clock": 0.0, "faraday": 0.0, "polalign": 0.0}}, {"station": "CS030HBA1", "removed": "no", "percentage_flagged": {"initial": 1.3886339082251082, "final": 16.69969341991342}, "percentage_flagged_solutions": {"bandpass": 0.390625, "clock": 0.0, "faraday": 0.0, "polalign": 0.0}}, {"station": "CS031HBA0", "removed": "no", "percentage_flagged": {"initial": 1.321100705194805, "final": 13.074754761904767}, "percentage_flagged_solutions": {"bandpass": 0.390625, "clock": 0.0, "faraday": 0.0, "polalign": 0.0}}, {"station": "CS031HBA1", "removed": "no", "percentage_flagged": {"initial": 1.3185974961038955, "final": 14.36352406926407}, "percentage_flagged_solutions": {"bandpass": 0.390625, "clock": 0.0, "faraday": 0.0, "polalign": 0.0}}, {"station": "CS032HBA0", "removed": "no", "percentage_flagged": {"initial": 1.0778298086580091, "final": 34.663358528138524}, "percentage_flagged_solutions": {"bandpass": 16.943359375, "clock": 0.0, "faraday": 0.0, "polalign": 0.0}}, {"station": "CS032HBA1", "removed": "no", "percentage_flagged": {"initial": 1.0478600463203465, "final": 26.28433125541126}, "percentage_flagged_solutions": {"bandpass": 11.23046875, "clock": 0.0, "faraday": 0.0, "polalign": 0.0}}, {"station": "CS101HBA0", "removed": "no", "percentage_flagged": {"initial": 1.2968583121212118, "final": 17.707388831168824}, "percentage_flagged_solutions": {"bandpass": 0.390625, "clock": 0.0, "faraday": 0.0, "polalign": 0.0}}, {"station": "CS101HBA1", "removed": "no", "percentage_flagged": {"initial": 1.2264667450216458, "final": 12.67495467532468}, "percentage_flagged_solutions": {"bandpass": 0.390625, "clock": 0.0, "faraday": 0.0, "polalign": 0.0}}, {"station": "CS103HBA0", "removed": "no", "percentage_flagged": {"initial": 1.2740362285714275, "final": 35.7679670995671}, "percentage_flagged_solutions": {"bandpass": 15.087890625, "clock": 0.0, "faraday": 0.0, "polalign": 0.0}}, {"station": "CS103HBA1", "removed": "no", "percentage_flagged": {"initial": 1.245797561904762, "final": 33.464837056277055}, "percentage_flagged_solutions": {"bandpass": 14.0625, "clock": 0.0, "faraday": 0.0, "polalign": 0.0}}, {"station": "CS201HBA0", "removed": "no", "percentage_flagged": {"initial": 1.3857643290043293, "final": 15.069143376623373}, "percentage_flagged_solutions": {"bandpass": 0.390625, "clock": 0.0, "faraday": 0.0, "polalign": 0.0}}, {"station": "CS201HBA1", "removed": "no", "percentage_flagged": {"initial": 1.3119994350649362, "final": 14.066155887445895}, "percentage_flagged_solutions": {"bandpass": 0.390625, "clock": 0.0, "faraday": 0.0, "polalign": 0.0}}, {"station": "CS301HBA0", "removed": "no", "percentage_flagged": {"initial": 1.541999801731601, "final": 15.283099783549789}, "percentage_flagged_solutions": {"bandpass": 0.390625, "clock": 0.0, "faraday": 0.0, "polalign": 0.0}}, {"station": "CS301HBA1", "removed": "no", "percentage_flagged": {"initial": 1.6119527294372296, "final": 14.274050346320344}, "percentage_flagged_solutions": {"bandpass": 0.390625, "clock": 0.0, "faraday": 0.0, "polalign": 0.0}}, {"station": "CS302HBA0", "removed": "no", "percentage_flagged": {"initial": 1.4679593913419924, "final": 14.853082207792204}, "percentage_flagged_solutions": {"bandpass": 0.390625, "clock": 0.0, "faraday": 0.0, "polalign": 0.0}}, {"station": "CS302HBA1", "removed": "no", "percentage_flagged": {"initial": 1.4970538346320357, "final": 13.812069090909098}, "percentage_flagged_solutions": {"bandpass": 0.390625, "clock": 0.0, "faraday": 0.0, "polalign": 0.0}}, {"station": "CS401HBA0", "removed": "no", "percentage_flagged": {"initial": 1.361200345887447, "final": 13.353505974025973}, "percentage_flagged_solutions": {"bandpass": 0.390625, "clock": 0.0, "faraday": 0.0, "polalign": 0.0}}, {"station": "CS401HBA1", "removed": "no", "percentage_flagged": {"initial": 1.3001928584415592, "final": 12.386643290043292}, "percentage_flagged_solutions": {"bandpass": 0.390625, "clock": 0.0, "faraday": 0.0, "polalign": 0.0}}, {"station": "CS501HBA0", "removed": "no", "percentage_flagged": {"initial": 1.3018819281385283, "final": 31.269260519480518}, "percentage_flagged_solutions": {"bandpass": 16.11328125, "clock": 0.0, "faraday": 0.0, "polalign": 0.0}}, {"station": "CS501HBA1", "removed": "no", "percentage_flagged": {"initial": 1.2894181069264083, "final": 33.82085662337662}, "percentage_flagged_solutions": {"bandpass": 18.994140625, "clock": 0.0, "faraday": 0.0, "polalign": 0.0}}, {"station": "DE601HBA", "removed": "no", "percentage_flagged": {"initial": 1.0819889458874479, "final": 8.93322077922078}, "percentage_flagged_solutions": {"bandpass": 0.390625, "clock": 0.0, "faraday": 0.0, "polalign": 0.0}}, {"station": "DE602HBA", "removed": "no", "percentage_flagged": {"initial": 1.9549603077922042, "final": 8.944997532467536}, "percentage_flagged_solutions": {"bandpass": 0.390625, "clock": 0.0, "faraday": 0.0, "polalign": 0.0}}, {"station": "DE603HBA", "removed": "no", "percentage_flagged": {"initial": 1.2769380891774893, "final": 8.41755896103896}, "percentage_flagged_solutions": {"bandpass": 0.390625, "clock": 0.0, "faraday": 0.0, "polalign": 0.0}}, {"station": "DE605HBA", "removed": "no", "percentage_flagged": {"initial": 1.776238163203461, "final": 9.140291255411258}, "percentage_flagged_solutions": {"bandpass": 0.390625, "clock": 0.0, "faraday": 0.0, "polalign": 0.0}}, {"station": "DE609HBA", "removed": "no", "percentage_flagged": {"initial": 1.3936864956709962, "final": 12.197199437229433}, "percentage_flagged_solutions": {"bandpass": 0.390625, "clock": 0.0, "faraday": 0.0, "polalign": 0.0}}, {"station": "IE613HBA", "removed": "no", "percentage_flagged": {"initial": 0.7908269740259743, "final": 8.461810692640693}, "percentage_flagged_solutions": {"bandpass": 0.390625, "clock": 0.0, "faraday": 0.0, "polalign": 0.0}}, {"station": "PL610HBA", "removed": "no", "percentage_flagged": {"initial": 0.923918602164503, "final": 8.363729090909088}, "percentage_flagged_solutions": {"bandpass": 0.390625, "clock": 0.0, "faraday": 0.0, "polalign": 0.0}}, {"station": "PL611HBA", "removed": "no", "percentage_flagged": {"initial": 0.8514187216450219, "final": 8.364608831168834}, "percentage_flagged_solutions": {"bandpass": 0.390625, "clock": 0.0, "faraday": 0.68359375, "polalign": 0.0}}, {"station": "PL612HBA", "removed": "no", "percentage_flagged": {"initial": 0.7835999783549787, "final": 100.0}, "percentage_flagged_solutions": {"bandpass": 100.0, "clock": 100.0, "faraday": 0.0, "polalign": 100.0}}, {"station": "RS106HBA", "removed": "no", "percentage_flagged": {"initial": 1.3261159909090912, "final": 10.938231774891777}, "percentage_flagged_solutions": {"bandpass": 0.390625, "clock": 0.0, "faraday": 0.0, "polalign": 0.0}}, {"station": "RS205HBA", "removed": "no", "percentage_flagged": {"initial": 1.2487338688311689, "final": 14.314753376623374}, "percentage_flagged_solutions": {"bandpass": 0.390625, "clock": 0.0, "faraday": 0.0, "polalign": 0.0}}, {"station": "RS208HBA", "removed": "no", "percentage_flagged": {"initial": 1.3909602887445887, "final": 9.8911645021645}, "percentage_flagged_solutions": {"bandpass": 0.390625, "clock": 0.0, "faraday": 0.0, "polalign": 0.0}}, {"station": "RS210HBA", "removed": "no", "percentage_flagged": {"initial": 1.4325390246753253, "final": 8.84652116883117}, "percentage_flagged_solutions": {"bandpass": 0.390625, "clock": 0.0, "faraday": 0.0, "polalign": 0.0}}, {"station": "RS305HBA", "removed": "no", "percentage_flagged": {"initial": 1.2025898393939403, "final": 12.376489956709952}, "percentage_flagged_solutions": {"bandpass": 0.390625, "clock": 0.0, "faraday": 0.0, "polalign": 0.0}}, {"station": "RS306HBA", "removed": "no", "percentage_flagged": {"initial": 1.169046856277056, "final": 10.864084805194803}, "percentage_flagged_solutions": {"bandpass": 0.390625, "clock": 100.0, "faraday": 0.0, "polalign": 0.0}}, {"station": "RS307HBA", "removed": "no", "percentage_flagged": {"initial": 1.2173541705627708, "final": 10.302559090909092}, "percentage_flagged_solutions": {"bandpass": 0.390625, "clock": 0.0, "faraday": 0.0, "polalign": 0.0}}, {"station": "RS310HBA", "removed": "no", "percentage_flagged": {"initial": 1.2157450822510825, "final": 35.58414562770563}, "percentage_flagged_solutions": {"bandpass": 19.189453125, "clock": 0.0, "faraday": 0.0, "polalign": 0.0}}, {"station": "RS406HBA", "removed": "no", "percentage_flagged": {"initial": 1.190758587445888, "final": 22.182178787878787}, "percentage_flagged_solutions": {"bandpass": 11.42578125, "clock": 0.0, "faraday": 0.0, "polalign": 0.0}}, {"station": "RS407HBA", "removed": "no", "percentage_flagged": {"initial": 1.007036626839828, "final": 40.31590683982684}, "percentage_flagged_solutions": {"bandpass": 17.138671875, "clock": 0.0, "faraday": 0.0, "polalign": 0.0}}, {"station": "RS409HBA", "removed": "no", "percentage_flagged": {"initial": 1.3294560099567108, "final": 19.60364484848485}, "percentage_flagged_solutions": {"bandpass": 0.390625, "clock": 0.0, "faraday": 0.0, "polalign": 0.0}}, {"station": "RS503HBA", "removed": "no", "percentage_flagged": {"initial": 1.1768019753246772, "final": 32.88917956709956}, "percentage_flagged_solutions": {"bandpass": 22.4609375, "clock": 0.0, "faraday": 0.0, "polalign": 0.0}}, {"station": "RS508HBA", "removed": "no", "percentage_flagged": {"initial": 1.1114021779220788, "final": 8.636393073593078}, "percentage_flagged_solutions": {"bandpass": 0.390625, "clock": 0.0, "faraday": 0.0, "polalign": 0.0}}, {"station": "RS509HBA", "removed": "no", "percentage_flagged": {"initial": 1.1161947212121226, "final": 8.908498917748917}, "percentage_flagged_solutions": {"bandpass": 0.390625, "clock": 0.0, "faraday": 0.0, "polalign": 0.0}}, {"station": "SE607HBA", "removed": "no", "percentage_flagged": {"initial": 0.9496925818181823, "final": 8.337131861471862}, "percentage_flagged_solutions": {"bandpass": 0.390625, "clock": 0.0, "faraday": 0.0, "polalign": 0.0}}, {"station": "UK608HBA", "removed": "no", "percentage_flagged": {"initial": 2.9318792753246727, "final": 11.824366147186144}, "percentage_flagged_solutions": {"bandpass": 0.390625, "clock": 0.0, "faraday": 0.0, "polalign": 0.0}}], "field_name": "3c295", "filtered_baselines_by_user": "*&", "close_sources": []}}}