{"metrics": {"LINC": {"run_type": "calibrator", "stations": [{"station": "CS001HBA0", "removed": "no", "percentage_flagged": {"initial": 0.7692709355844155, "final": 7.569655367965368}, "percentage_flagged_solutions": {"bandpass": 0.390625, "clock": 0.0, "faraday": 0.0, "polalign": 0.0}}, {"station": "CS001HBA1", "removed": "no", "percentage_flagged": {"initial": 0.7767784466666658, "final": 7.9112070129870125}, "percentage_flagged_solutions": {"bandpass": 0.390625, "clock": 0.0, "faraday": 0.0, "polalign": 0.0}}, {"station": "CS002HBA0", "removed": "no", "percentage_flagged": {"initial": 0.8317856044155851, "final": 7.873971774891777}, "percentage_flagged_solutions": {"bandpass": 0.390625, "clock": 0.0, "faraday": 0.0, "polalign": 0.0}}, {"station": "CS002HBA1", "removed": "no", "percentage_flagged": {"initial": 7.06708942424243, "final": 16.840808051948052}, "percentage_flagged_solutions": {"bandpass": 0.390625, "clock": 0.0, "faraday": 0.0, "polalign": 0.0}}, {"station": "CS003HBA0", "removed": "no", "percentage_flagged": {"initial": 0.7703510219913416, "final": 7.811367142857141}, "percentage_flagged_solutions": {"bandpass": 0.390625, "clock": 0.0, "faraday": 0.0, "polalign": 0.0}}, {"station": "CS003HBA1", "removed": "no", "percentage_flagged": {"initial": 1.0377250912987013, "final": 8.560889783549786}, "percentage_flagged_solutions": {"bandpass": 0.390625, "clock": 0.0, "faraday": 0.0, "polalign": 0.0}}, {"station": "CS004HBA0", "removed": "no", "percentage_flagged": {"initial": 0.8017237347186146, "final": 7.543183506493503}, "percentage_flagged_solutions": {"bandpass": 0.390625, "clock": 0.0, "faraday": 0.0, "polalign": 0.0}}, {"station": "CS004HBA1", "removed": "no", "percentage_flagged": {"initial": 1.0169287041125552, "final": 10.704018961038955}, "percentage_flagged_solutions": {"bandpass": 0.390625, "clock": 0.0, "faraday": 0.0, "polalign": 0.0}}, {"station": "CS005HBA0", "removed": "no", "percentage_flagged": {"initial": 0.8776250706060609, "final": 8.566688138528137}, "percentage_flagged_solutions": {"bandpass": 0.390625, "clock": 0.0, "faraday": 0.0, "polalign": 0.0}}, {"station": "CS005HBA1", "removed": "no", "percentage_flagged": {"initial": 0.8401532697402601, "final": 8.306647359307357}, "percentage_flagged_solutions": {"bandpass": 0.390625, "clock": 0.0, "faraday": 0.0, "polalign": 0.0}}, {"station": "CS006HBA0", "removed": "no", "percentage_flagged": {"initial": 0.7816075278354986, "final": 10.049771385281387}, "percentage_flagged_solutions": {"bandpass": 0.390625, "clock": 0.0, "faraday": 0.0, "polalign": 0.0}}, {"station": "CS006HBA1", "removed": "no", "percentage_flagged": {"initial": 0.8921111438961041, "final": 10.04954987012987}, "percentage_flagged_solutions": {"bandpass": 0.390625, "clock": 0.0, "faraday": 0.0, "polalign": 0.0}}, {"station": "CS007HBA0", "removed": "no", "percentage_flagged": {"initial": 0.8471053843290046, "final": 7.919845714285718}, "percentage_flagged_solutions": {"bandpass": 0.390625, "clock": 0.0, "faraday": 0.0, "polalign": 0.0}}, {"station": "CS007HBA1", "removed": "no", "percentage_flagged": {"initial": 0.8265865444155844, "final": 8.320803679653677}, "percentage_flagged_solutions": {"bandpass": 0.390625, "clock": 0.0, "faraday": 0.0, "polalign": 0.0}}, {"station": "CS011HBA0", "removed": "no", "percentage_flagged": {"initial": 0.8310644709090909, "final": 7.536728614718611}, "percentage_flagged_solutions": {"bandpass": 0.390625, "clock": 0.0, "faraday": 0.0, "polalign": 0.0}}, {"station": "CS011HBA1", "removed": "no", "percentage_flagged": {"initial": 0.826226000692641, "final": 7.530361125541124}, "percentage_flagged_solutions": {"bandpass": 0.390625, "clock": 0.0, "faraday": 0.0, "polalign": 0.0}}, {"station": "CS013HBA0", "removed": "no", "percentage_flagged": {"initial": 0.8049781772294371, "final": 10.249290043290046}, "percentage_flagged_solutions": {"bandpass": 0.390625, "clock": 0.0, "faraday": 0.0, "polalign": 0.0}}, {"station": "CS013HBA1", "removed": "no", "percentage_flagged": {"initial": 0.7965344026406926, "final": 10.082827402597399}, "percentage_flagged_solutions": {"bandpass": 0.390625, "clock": 0.0, "faraday": 0.0, "polalign": 0.0}}, {"station": "CS017HBA0", "removed": "no", "percentage_flagged": {"initial": 0.7801882026406924, "final": 10.320452900432903}, "percentage_flagged_solutions": {"bandpass": 0.390625, "clock": 0.0, "faraday": 0.0, "polalign": 0.0}}, {"station": "CS017HBA1", "removed": "no", "percentage_flagged": {"initial": 0.8465765230303031, "final": 10.360372207792208}, "percentage_flagged_solutions": {"bandpass": 0.390625, "clock": 0.0, "faraday": 0.0, "polalign": 0.0}}, {"station": "CS021HBA0", "removed": "no", "percentage_flagged": {"initial": 0.8861322828571429, "final": 9.924838095238094}, "percentage_flagged_solutions": {"bandpass": 0.390625, "clock": 0.0, "faraday": 0.0, "polalign": 0.0}}, {"station": "CS021HBA1", "removed": "no", "percentage_flagged": {"initial": 0.9551183522077921, "final": 10.585771471861474}, "percentage_flagged_solutions": {"bandpass": 0.390625, "clock": 0.0, "faraday": 0.0, "polalign": 0.0}}, {"station": "CS024HBA0", "removed": "no", "percentage_flagged": {"initial": 1.2831183979653686, "final": 8.178453809523807}, "percentage_flagged_solutions": {"bandpass": 0.390625, "clock": 0.0, "faraday": 0.0, "polalign": 0.0}}, {"station": "CS024HBA1", "removed": "no", "percentage_flagged": {"initial": 1.3048847995670996, "final": 9.208660649350648}, "percentage_flagged_solutions": {"bandpass": 0.390625, "clock": 0.0, "faraday": 0.0, "polalign": 0.0}}, {"station": "CS026HBA0", "removed": "no", "percentage_flagged": {"initial": 1.4342534951515158, "final": 7.491496536796532}, "percentage_flagged_solutions": {"bandpass": 0.390625, "clock": 0.0, "faraday": 0.0, "polalign": 0.0}}, {"station": "CS026HBA1", "removed": "no", "percentage_flagged": {"initial": 1.4251371339826844, "final": 8.49093142857143}, "percentage_flagged_solutions": {"bandpass": 0.390625, "clock": 0.0, "faraday": 0.0, "polalign": 0.0}}, {"station": "CS028HBA0", "removed": "no", "percentage_flagged": {"initial": 1.3026769949783545, "final": 9.236778181818183}, "percentage_flagged_solutions": {"bandpass": 0.390625, "clock": 0.0, "faraday": 0.0, "polalign": 0.0}}, {"station": "CS028HBA1", "removed": "no", "percentage_flagged": {"initial": 1.2867790541991335, "final": 9.964363463203464}, "percentage_flagged_solutions": {"bandpass": 0.390625, "clock": 0.0, "faraday": 0.0, "polalign": 0.0}}, {"station": "CS030HBA0", "removed": "no", "percentage_flagged": {"initial": 1.2329934993939398, "final": 8.77869411255411}, "percentage_flagged_solutions": {"bandpass": 0.390625, "clock": 0.0, "faraday": 0.0, "polalign": 0.0}}, {"station": "CS030HBA1", "removed": "no", "percentage_flagged": {"initial": 1.2762400938961032, "final": 9.777698484848488}, "percentage_flagged_solutions": {"bandpass": 0.390625, "clock": 0.0, "faraday": 0.0, "polalign": 0.0}}, {"station": "CS031HBA0", "removed": "no", "percentage_flagged": {"initial": 1.2297079663636368, "final": 7.655980952380956}, "percentage_flagged_solutions": {"bandpass": 0.390625, "clock": 0.0, "faraday": 0.0, "polalign": 0.0}}, {"station": "CS031HBA1", "removed": "no", "percentage_flagged": {"initial": 1.2392652572727265, "final": 8.187113506493501}, "percentage_flagged_solutions": {"bandpass": 0.390625, "clock": 0.0, "faraday": 0.0, "polalign": 0.0}}, {"station": "CS032HBA0", "removed": "no", "percentage_flagged": {"initial": 0.8684726263636363, "final": 8.449837099567095}, "percentage_flagged_solutions": {"bandpass": 0.390625, "clock": 0.0, "faraday": 0.0, "polalign": 0.0}}, {"station": "CS032HBA1", "removed": "no", "percentage_flagged": {"initial": 0.8106230407359305, "final": 8.886157705627706}, "percentage_flagged_solutions": {"bandpass": 0.390625, "clock": 0.0, "faraday": 0.0, "polalign": 0.0}}, {"station": "CS101HBA0", "removed": "no", "percentage_flagged": {"initial": 1.3625884746320356, "final": 11.030772424242429}, "percentage_flagged_solutions": {"bandpass": 0.390625, "clock": 0.0, "faraday": 0.0, "polalign": 0.0}}, {"station": "CS101HBA1", "removed": "no", "percentage_flagged": {"initial": 1.4057170887878792, "final": 10.895090216450212}, "percentage_flagged_solutions": {"bandpass": 0.390625, "clock": 0.0, "faraday": 0.0, "polalign": 0.0}}, {"station": "CS103HBA0", "removed": "no", "percentage_flagged": {"initial": 1.3258647063203466, "final": 7.540600649350651}, "percentage_flagged_solutions": {"bandpass": 0.390625, "clock": 0.0, "faraday": 0.0, "polalign": 0.0}}, {"station": "CS103HBA1", "removed": "no", "percentage_flagged": {"initial": 1.3765989481385272, "final": 7.44694017316017}, "percentage_flagged_solutions": {"bandpass": 0.390625, "clock": 0.0, "faraday": 0.0, "polalign": 0.0}}, {"station": "CS201HBA0", "removed": "no", "percentage_flagged": {"initial": 1.4293854767532466, "final": 9.683866103896102}, "percentage_flagged_solutions": {"bandpass": 0.390625, "clock": 0.0, "faraday": 0.0, "polalign": 0.0}}, {"station": "CS201HBA1", "removed": "no", "percentage_flagged": {"initial": 1.3897538330735943, "final": 8.473888961038954}, "percentage_flagged_solutions": {"bandpass": 0.390625, "clock": 0.0, "faraday": 0.0, "polalign": 0.0}}, {"station": "CS301HBA0", "removed": "no", "percentage_flagged": {"initial": 1.172428959956709, "final": 11.027884155844152}, "percentage_flagged_solutions": {"bandpass": 0.390625, "clock": 0.0, "faraday": 0.0, "polalign": 0.0}}, {"station": "CS301HBA1", "removed": "no", "percentage_flagged": {"initial": 1.1909003023809526, "final": 11.299830822510813}, "percentage_flagged_solutions": {"bandpass": 0.634765625, "clock": 0.0, "faraday": 0.0, "polalign": 0.0}}, {"station": "CS302HBA0", "removed": "no", "percentage_flagged": {"initial": 1.2631630724675336, "final": 9.194542900432902}, "percentage_flagged_solutions": {"bandpass": 0.390625, "clock": 0.0, "faraday": 0.0, "polalign": 0.0}}, {"station": "CS302HBA1", "removed": "no", "percentage_flagged": {"initial": 1.3203900819047618, "final": 10.107903419913425}, "percentage_flagged_solutions": {"bandpass": 0.390625, "clock": 0.0, "faraday": 0.0, "polalign": 0.0}}, {"station": "CS401HBA0", "removed": "no", "percentage_flagged": {"initial": 1.3103647258008646, "final": 10.40674199134199}, "percentage_flagged_solutions": {"bandpass": 0.390625, "clock": 0.0, "faraday": 0.0, "polalign": 0.0}}, {"station": "CS401HBA1", "removed": "no", "percentage_flagged": {"initial": 1.2066952807792204, "final": 9.028295974025982}, "percentage_flagged_solutions": {"bandpass": 0.390625, "clock": 0.0, "faraday": 0.0, "polalign": 0.0}}, {"station": "CS501HBA0", "removed": "no", "percentage_flagged": {"initial": 1.5236046776623378, "final": 17.312097056277054}, "percentage_flagged_solutions": {"bandpass": 4.8828125, "clock": 0.0, "faraday": 0.0, "polalign": 0.0}}, {"station": "CS501HBA1", "removed": "no", "percentage_flagged": {"initial": 1.544555674112553, "final": 9.969442857142855}, "percentage_flagged_solutions": {"bandpass": 0.390625, "clock": 0.0, "faraday": 0.0, "polalign": 0.0}}, {"station": "DE601HBA", "removed": "no", "percentage_flagged": {"initial": 1.164913939696969, "final": 6.3349898701298715}, "percentage_flagged_solutions": {"bandpass": 0.390625, "clock": 0.0, "faraday": 0.0, "polalign": 0.0}}, {"station": "DE602HBA", "removed": "no", "percentage_flagged": {"initial": 1.1747806558008658, "final": 6.74414082251082}, "percentage_flagged_solutions": {"bandpass": 0.390625, "clock": 0.0, "faraday": 0.0, "polalign": 0.0}}, {"station": "DE603HBA", "removed": "no", "percentage_flagged": {"initial": 0.9363006770129878, "final": 6.647917748917748}, "percentage_flagged_solutions": {"bandpass": 0.390625, "clock": 0.0, "faraday": 0.0, "polalign": 0.0}}, {"station": "DE604HBA", "removed": "no", "percentage_flagged": {"initial": 1.1738392858008664, "final": 7.085663852813849}, "percentage_flagged_solutions": {"bandpass": 0.390625, "clock": 0.0, "faraday": 0.0, "polalign": 0.0}}, {"station": "DE605HBA", "removed": "no", "percentage_flagged": {"initial": 1.7949968054545458, "final": 7.189131212121214}, "percentage_flagged_solutions": {"bandpass": 0.390625, "clock": 0.0, "faraday": 0.0, "polalign": 0.0}}, {"station": "DE609HBA", "removed": "no", "percentage_flagged": {"initial": 0.9327983314718602, "final": 6.770601515151515}, "percentage_flagged_solutions": {"bandpass": 0.390625, "clock": 0.0, "faraday": 0.0, "polalign": 0.0}}, {"station": "FR606HBA", "removed": "no", "percentage_flagged": {"initial": 0.8209920975757578, "final": 6.005937965367963}, "percentage_flagged_solutions": {"bandpass": 0.390625, "clock": 0.0, "faraday": 0.0, "polalign": 0.0}}, {"station": "IE613HBA", "removed": "no", "percentage_flagged": {"initial": 0.6448923411255412, "final": 100.0}, "percentage_flagged_solutions": {"bandpass": 100.0, "clock": 100.0, "faraday": 90.667724609375, "polalign": 0.0}}, {"station": "PL610HBA", "removed": "no", "percentage_flagged": {"initial": 0.6726920625541127, "final": 6.168060519480522}, "percentage_flagged_solutions": {"bandpass": 0.390625, "clock": 0.0, "faraday": 0.68359375, "polalign": 0.0}}, {"station": "PL611HBA", "removed": "no", "percentage_flagged": {"initial": 0.7729050663203462, "final": 6.2957860606060585}, "percentage_flagged_solutions": {"bandpass": 0.390625, "clock": 0.0, "faraday": 0.68359375, "polalign": 0.0}}, {"station": "PL612HBA", "removed": "no", "percentage_flagged": {"initial": 0.6974866171861476, "final": 100.0}, "percentage_flagged_solutions": {"bandpass": 100.0, "clock": 100.0, "faraday": 84.66796875, "polalign": 0.0}}, {"station": "RS106HBA", "removed": "no", "percentage_flagged": {"initial": 1.2957957253679653, "final": 6.400521168831166}, "percentage_flagged_solutions": {"bandpass": 0.390625, "clock": 0.0, "faraday": 0.0, "polalign": 0.0}}, {"station": "RS205HBA", "removed": "no", "percentage_flagged": {"initial": 1.292439142770563, "final": 6.4465014285714215}, "percentage_flagged_solutions": {"bandpass": 0.390625, "clock": 0.0, "faraday": 0.0, "polalign": 0.0}}, {"station": "RS208HBA", "removed": "no", "percentage_flagged": {"initial": 1.3016768030735928, "final": 6.254446233766234}, "percentage_flagged_solutions": {"bandpass": 0.390625, "clock": 0.0, "faraday": 0.0, "polalign": 0.0}}, {"station": "RS210HBA", "removed": "no", "percentage_flagged": {"initial": 1.0083021520779216, "final": 6.6769432467532415}, "percentage_flagged_solutions": {"bandpass": 0.390625, "clock": 0.0, "faraday": 0.0, "polalign": 0.0}}, {"station": "RS305HBA", "removed": "no", "percentage_flagged": {"initial": 8.123151137662333, "final": 20.235599437229435}, "percentage_flagged_solutions": {"bandpass": 0.390625, "clock": 0.0, "faraday": 0.0, "polalign": 0.0}}, {"station": "RS306HBA", "removed": "no", "percentage_flagged": {"initial": 1.1207127903463197, "final": 6.35283294372294}, "percentage_flagged_solutions": {"bandpass": 0.390625, "clock": 0.0, "faraday": 0.0, "polalign": 0.0}}, {"station": "RS307HBA", "removed": "no", "percentage_flagged": {"initial": 1.24883511047619, "final": 6.227593722943717}, "percentage_flagged_solutions": {"bandpass": 0.390625, "clock": 0.0, "faraday": 0.0, "polalign": 0.0}}, {"station": "RS310HBA", "removed": "no", "percentage_flagged": {"initial": 1.1505204749350648, "final": 24.484741255411254}, "percentage_flagged_solutions": {"bandpass": 10.009765625, "clock": 0.0, "faraday": 0.0, "polalign": 0.0}}, {"station": "RS406HBA", "removed": "no", "percentage_flagged": {"initial": 1.1530951896969703, "final": 20.763084502164496}, "percentage_flagged_solutions": {"bandpass": 7.958984375, "clock": 0.0, "faraday": 0.0, "polalign": 0.0}}, {"station": "RS407HBA", "removed": "no", "percentage_flagged": {"initial": 1.2052671619047615, "final": 6.370627099567093}, "percentage_flagged_solutions": {"bandpass": 0.390625, "clock": 0.0, "faraday": 0.0, "polalign": 0.0}}, {"station": "RS409HBA", "removed": "no", "percentage_flagged": {"initial": 1.097243969047619, "final": 6.626945151515154}, "percentage_flagged_solutions": {"bandpass": 0.390625, "clock": 0.0, "faraday": 0.0, "polalign": 0.0}}, {"station": "RS503HBA", "removed": "no", "percentage_flagged": {"initial": 1.171107966852814, "final": 34.974766839826835}, "percentage_flagged_solutions": {"bandpass": 23.876953125, "clock": 0.0, "faraday": 0.0, "polalign": 0.0}}, {"station": "RS508HBA", "removed": "no", "percentage_flagged": {"initial": 1.132222877619047, "final": 6.325425411255405}, "percentage_flagged_solutions": {"bandpass": 0.390625, "clock": 0.0, "faraday": 0.0, "polalign": 0.0}}, {"station": "RS509HBA", "removed": "no", "percentage_flagged": {"initial": 1.2586047013116874, "final": 7.381019913419914}, "percentage_flagged_solutions": {"bandpass": 0.390625, "clock": 0.0, "faraday": 0.0, "polalign": 0.0}}, {"station": "SE607HBA", "removed": "no", "percentage_flagged": {"initial": 0.73806333017316, "final": 5.85927792207792}, "percentage_flagged_solutions": {"bandpass": 0.390625, "clock": 0.0, "faraday": 0.0, "polalign": 0.0}}, {"station": "UK608HBA", "removed": "no", "percentage_flagged": {"initial": 1.96553171034632, "final": 8.326400909090905}, "percentage_flagged_solutions": {"bandpass": 0.390625, "clock": 0.0, "faraday": 0.0, "polalign": 0.0}}], "field_name": "POINT", "filtered_baselines_by_user": "*&", "close_sources": []}}}