{"metrics": {"LINC": {"run_type": "calibrator", "stations": [{"station": "CS002HBA0", "removed": "no", "percentage_flagged": {"initial": 6.148482164502157, "final": 36.81801731601727}, "percentage_flagged_solutions": {"bandpass": 0.390625, "clock": 0.0, "faraday": 0.0, "polalign": 0.0}}, {"station": "CS002HBA1", "removed": "no", "percentage_flagged": {"initial": 6.224093246753249, "final": 33.89379523809525}, "percentage_flagged_solutions": {"bandpass": 0.390625, "clock": 0.0, "faraday": 0.0, "polalign": 0.0}}, {"station": "CS003HBA0", "removed": "no", "percentage_flagged": {"initial": 6.274964718614717, "final": 35.81755194805197}, "percentage_flagged_solutions": {"bandpass": 0.390625, "clock": 0.0, "faraday": 0.0, "polalign": 0.0}}, {"station": "CS003HBA1", "removed": "no", "percentage_flagged": {"initial": 6.282327705627706, "final": 36.06345238095237}, "percentage_flagged_solutions": {"bandpass": 0.390625, "clock": 0.0, "faraday": 0.0, "polalign": 0.0}}, {"station": "CS004HBA0", "removed": "no", "percentage_flagged": {"initial": 6.142822424242424, "final": 36.97945800865804}, "percentage_flagged_solutions": {"bandpass": 0.390625, "clock": 0.0, "faraday": 0.0, "polalign": 0.0}}, {"station": "CS004HBA1", "removed": "no", "percentage_flagged": {"initial": 6.178582467532467, "final": 32.54895584415584}, "percentage_flagged_solutions": {"bandpass": 0.390625, "clock": 0.0, "faraday": 0.0, "polalign": 0.0}}, {"station": "CS005HBA0", "removed": "no", "percentage_flagged": {"initial": 6.158794588744584, "final": 33.812380519480506}, "percentage_flagged_solutions": {"bandpass": 0.390625, "clock": 0.0, "faraday": 0.0, "polalign": 0.0}}, {"station": "CS005HBA1", "removed": "no", "percentage_flagged": {"initial": 6.159146060606056, "final": 30.397578354978354}, "percentage_flagged_solutions": {"bandpass": 0.390625, "clock": 0.0, "faraday": 0.0, "polalign": 0.0}}, {"station": "CS006HBA0", "removed": "no", "percentage_flagged": {"initial": 6.201203636363634, "final": 36.787185281385284}, "percentage_flagged_solutions": {"bandpass": 0.390625, "clock": 0.0, "faraday": 0.0, "polalign": 0.0}}, {"station": "CS006HBA1", "removed": "no", "percentage_flagged": {"initial": 6.158742857142855, "final": 32.78559004329005}, "percentage_flagged_solutions": {"bandpass": 0.390625, "clock": 0.0, "faraday": 0.0, "polalign": 0.0}}, {"station": "CS007HBA0", "removed": "no", "percentage_flagged": {"initial": 6.143915367965368, "final": 34.07374761904764}, "percentage_flagged_solutions": {"bandpass": 0.390625, "clock": 0.0, "faraday": 0.0, "polalign": 0.0}}, {"station": "CS007HBA1", "removed": "no", "percentage_flagged": {"initial": 6.196007575757568, "final": 36.26167922077922}, "percentage_flagged_solutions": {"bandpass": 0.390625, "clock": 0.0, "faraday": 0.0, "polalign": 0.0}}, {"station": "CS011HBA0", "removed": "no", "percentage_flagged": {"initial": 6.405769956709954, "final": 35.617737662337674}, "percentage_flagged_solutions": {"bandpass": 0.390625, "clock": 0.0, "faraday": 0.0, "polalign": 0.0}}, {"station": "CS011HBA1", "removed": "no", "percentage_flagged": {"initial": 6.235795627705625, "final": 37.73446666666665}, "percentage_flagged_solutions": {"bandpass": 0.390625, "clock": 0.0, "faraday": 0.0, "polalign": 0.0}}, {"station": "CS013HBA0", "removed": "no", "percentage_flagged": {"initial": 6.162741298701297, "final": 37.35753549783548}, "percentage_flagged_solutions": {"bandpass": 0.390625, "clock": 0.0, "faraday": 0.0, "polalign": 0.0}}, {"station": "CS013HBA1", "removed": "no", "percentage_flagged": {"initial": 6.213320822510822, "final": 36.89418528138528}, "percentage_flagged_solutions": {"bandpass": 0.390625, "clock": 0.0, "faraday": 0.0, "polalign": 0.0}}, {"station": "CS017HBA0", "removed": "no", "percentage_flagged": {"initial": 6.326666666666661, "final": 34.397967532467575}, "percentage_flagged_solutions": {"bandpass": 0.390625, "clock": 0.0, "faraday": 0.0, "polalign": 0.0}}, {"station": "CS017HBA1", "removed": "no", "percentage_flagged": {"initial": 6.155548008658009, "final": 30.34246450216451}, "percentage_flagged_solutions": {"bandpass": 0.390625, "clock": 0.0, "faraday": 0.0, "polalign": 0.0}}, {"station": "CS021HBA0", "removed": "no", "percentage_flagged": {"initial": 6.178970086580082, "final": 34.978622510822504}, "percentage_flagged_solutions": {"bandpass": 0.390625, "clock": 0.0, "faraday": 0.0, "polalign": 0.0}}, {"station": "CS021HBA1", "removed": "no", "percentage_flagged": {"initial": 6.289951471861471, "final": 35.45668917748917}, "percentage_flagged_solutions": {"bandpass": 0.390625, "clock": 0.0, "faraday": 0.0, "polalign": 0.0}}, {"station": "CS024HBA0", "removed": "no", "percentage_flagged": {"initial": 6.288762077922078, "final": 36.40164675324673}, "percentage_flagged_solutions": {"bandpass": 0.390625, "clock": 0.0, "faraday": 0.0, "polalign": 0.0}}, {"station": "CS024HBA1", "removed": "no", "percentage_flagged": {"initial": 6.262100822510817, "final": 35.23459090909087}, "percentage_flagged_solutions": {"bandpass": 0.390625, "clock": 0.0, "faraday": 0.0, "polalign": 0.0}}, {"station": "CS026HBA0", "removed": "no", "percentage_flagged": {"initial": 6.356760043290042, "final": 35.36441601731603}, "percentage_flagged_solutions": {"bandpass": 0.390625, "clock": 0.0, "faraday": 0.0, "polalign": 0.0}}, {"station": "CS026HBA1", "removed": "no", "percentage_flagged": {"initial": 6.251239264069264, "final": 34.630891774891744}, "percentage_flagged_solutions": {"bandpass": 0.390625, "clock": 0.0, "faraday": 0.0, "polalign": 0.0}}, {"station": "CS028HBA0", "removed": "no", "percentage_flagged": {"initial": 6.271537186147184, "final": 35.99730043290042}, "percentage_flagged_solutions": {"bandpass": 0.390625, "clock": 0.0, "faraday": 0.0, "polalign": 0.0}}, {"station": "CS028HBA1", "removed": "no", "percentage_flagged": {"initial": 6.235267965367964, "final": 34.88693333333334}, "percentage_flagged_solutions": {"bandpass": 0.390625, "clock": 0.0, "faraday": 0.0, "polalign": 0.0}}, {"station": "CS030HBA0", "removed": "no", "percentage_flagged": {"initial": 6.267343722943722, "final": 33.92149004329004}, "percentage_flagged_solutions": {"bandpass": 0.390625, "clock": 0.0, "faraday": 0.0, "polalign": 0.0}}, {"station": "CS030HBA1", "removed": "no", "percentage_flagged": {"initial": 6.283722770562769, "final": 33.08835021645022}, "percentage_flagged_solutions": {"bandpass": 0.390625, "clock": 0.0, "faraday": 0.0, "polalign": 0.0}}, {"station": "CS031HBA0", "removed": "no", "percentage_flagged": {"initial": 6.271086536796535, "final": 36.29489999999997}, "percentage_flagged_solutions": {"bandpass": 0.390625, "clock": 0.0, "faraday": 0.0, "polalign": 0.0}}, {"station": "CS031HBA1", "removed": "no", "percentage_flagged": {"initial": 6.219630389610383, "final": 31.28794329004331}, "percentage_flagged_solutions": {"bandpass": 0.390625, "clock": 0.0, "faraday": 0.0, "polalign": 0.0}}, {"station": "CS101HBA0", "removed": "no", "percentage_flagged": {"initial": 6.274779004328999, "final": 35.01164805194805}, "percentage_flagged_solutions": {"bandpass": 0.390625, "clock": 0.0, "faraday": 0.0, "polalign": 0.0}}, {"station": "CS101HBA1", "removed": "no", "percentage_flagged": {"initial": 6.597168354978356, "final": 39.0665225108225}, "percentage_flagged_solutions": {"bandpass": 0.390625, "clock": 0.0, "faraday": 0.0, "polalign": 0.0}}, {"station": "CS103HBA0", "removed": "no", "percentage_flagged": {"initial": 6.29932766233766, "final": 32.77893203463204}, "percentage_flagged_solutions": {"bandpass": 0.390625, "clock": 0.0, "faraday": 0.0, "polalign": 0.0}}, {"station": "CS103HBA1", "removed": "no", "percentage_flagged": {"initial": 6.228697662337663, "final": 34.635459307359326}, "percentage_flagged_solutions": {"bandpass": 0.390625, "clock": 0.0, "faraday": 0.0, "polalign": 0.0}}, {"station": "CS201HBA0", "removed": "no", "percentage_flagged": {"initial": 6.257052251082243, "final": 35.46052727272729}, "percentage_flagged_solutions": {"bandpass": 0.390625, "clock": 0.0, "faraday": 0.0, "polalign": 0.0}}, {"station": "CS201HBA1", "removed": "no", "percentage_flagged": {"initial": 6.204908701298701, "final": 36.07836709956712}, "percentage_flagged_solutions": {"bandpass": 0.390625, "clock": 0.0, "faraday": 0.0, "polalign": 0.0}}, {"station": "CS301HBA0", "removed": "no", "percentage_flagged": {"initial": 6.26546835497835, "final": 31.109057142857143}, "percentage_flagged_solutions": {"bandpass": 0.390625, "clock": 0.0, "faraday": 0.0, "polalign": 0.0}}, {"station": "CS301HBA1", "removed": "no", "percentage_flagged": {"initial": 6.476431255411254, "final": 32.97347748917749}, "percentage_flagged_solutions": {"bandpass": 0.390625, "clock": 0.0, "faraday": 0.0, "polalign": 0.0}}, {"station": "CS302HBA0", "removed": "no", "percentage_flagged": {"initial": 6.38834948051948, "final": 31.088073160173153}, "percentage_flagged_solutions": {"bandpass": 0.390625, "clock": 0.0, "faraday": 0.0, "polalign": 0.0}}, {"station": "CS302HBA1", "removed": "no", "percentage_flagged": {"initial": 6.347652597402592, "final": 34.5402376623377}, "percentage_flagged_solutions": {"bandpass": 0.390625, "clock": 0.0, "faraday": 0.0, "polalign": 0.0}}, {"station": "CS401HBA0", "removed": "no", "percentage_flagged": {"initial": 6.398854242424242, "final": 36.78462251082254}, "percentage_flagged_solutions": {"bandpass": 0.390625, "clock": 0.0, "faraday": 0.0, "polalign": 0.0}}, {"station": "CS401HBA1", "removed": "no", "percentage_flagged": {"initial": 6.248535108225106, "final": 35.275099134199095}, "percentage_flagged_solutions": {"bandpass": 0.390625, "clock": 0.0, "faraday": 0.0, "polalign": 0.0}}, {"station": "CS501HBA0", "removed": "no", "percentage_flagged": {"initial": 6.289916363636361, "final": 32.4243852813853}, "percentage_flagged_solutions": {"bandpass": 0.390625, "clock": 0.0, "faraday": 0.0, "polalign": 0.0}}, {"station": "CS501HBA1", "removed": "no", "percentage_flagged": {"initial": 6.406748961038962, "final": 35.14206233766238}, "percentage_flagged_solutions": {"bandpass": 0.390625, "clock": 0.0, "faraday": 0.0, "polalign": 0.0}}, {"station": "DE601HBA", "removed": "no", "percentage_flagged": {"initial": 6.197138181818178, "final": 52.756134632034644}, "percentage_flagged_solutions": {"bandpass": 0.390625, "clock": 0.0, "faraday": 0.0, "polalign": 0.0}}, {"station": "DE602HBA", "removed": "no", "percentage_flagged": {"initial": 100.0, "final": 100.0}, "percentage_flagged_solutions": {"bandpass": 100.0, "clock": 100.0, "faraday": 8.0078125, "polalign": 0.0}}, {"station": "DE603HBA", "removed": "no", "percentage_flagged": {"initial": 5.927803852813851, "final": 44.51385411255414}, "percentage_flagged_solutions": {"bandpass": 0.390625, "clock": 0.0, "faraday": 0.0, "polalign": 0.0}}, {"station": "DE605HBA", "removed": "no", "percentage_flagged": {"initial": 6.547153116883112, "final": 55.238723376623355}, "percentage_flagged_solutions": {"bandpass": 0.390625, "clock": 0.0, "faraday": 0.0, "polalign": 0.0}}, {"station": "DE609HBA", "removed": "no", "percentage_flagged": {"initial": 100.0, "final": 100.0}, "percentage_flagged_solutions": {"bandpass": 100.0, "clock": 100.0, "faraday": 8.0078125, "polalign": 0.0}}, {"station": "FR606HBA", "removed": "no", "percentage_flagged": {"initial": 6.037986320346322, "final": 47.21156536796542}, "percentage_flagged_solutions": {"bandpass": 0.390625, "clock": 0.0, "faraday": 0.0, "polalign": 0.0}}, {"station": "IE613HBA", "removed": "no", "percentage_flagged": {"initial": 5.982997359307363, "final": 100.0}, "percentage_flagged_solutions": {"bandpass": 100.0, "clock": 100.0, "faraday": 99.33319091796875, "polalign": 0.0}}, {"station": "LV614HBA", "removed": "no", "percentage_flagged": {"initial": 5.951826493506486, "final": 100.0}, "percentage_flagged_solutions": {"bandpass": 100.0, "clock": 100.0, "faraday": 68.6767578125, "polalign": 0.0}}, {"station": "PL610HBA", "removed": "no", "percentage_flagged": {"initial": 5.950504199134199, "final": 100.0}, "percentage_flagged_solutions": {"bandpass": 100.0, "clock": 100.0, "faraday": 98.6663818359375, "polalign": 0.0}}, {"station": "PL611HBA", "removed": "no", "percentage_flagged": {"initial": 100.0, "final": 100.0}, "percentage_flagged_solutions": {"bandpass": 100.0, "clock": 100.0, "faraday": 8.0078125, "polalign": 0.0}}, {"station": "PL612HBA", "removed": "no", "percentage_flagged": {"initial": 5.945540389610389, "final": 100.0}, "percentage_flagged_solutions": {"bandpass": 100.0, "clock": 100.0, "faraday": 100.0, "polalign": 0.0}}, {"station": "RS106HBA", "removed": "no", "percentage_flagged": {"initial": 6.2032615584415565, "final": 34.74685324675323}, "percentage_flagged_solutions": {"bandpass": 0.390625, "clock": 0.0, "faraday": 0.0, "polalign": 0.0}}, {"station": "RS205HBA", "removed": "no", "percentage_flagged": {"initial": 6.16789952380952, "final": 30.747075324675322}, "percentage_flagged_solutions": {"bandpass": 0.390625, "clock": 0.0, "faraday": 0.0, "polalign": 0.0}}, {"station": "RS208HBA", "removed": "no", "percentage_flagged": {"initial": 6.274862467532463, "final": 29.790650216450192}, "percentage_flagged_solutions": {"bandpass": 0.390625, "clock": 0.0, "faraday": 0.0, "polalign": 0.0}}, {"station": "RS210HBA", "removed": "no", "percentage_flagged": {"initial": 6.395351731601728, "final": 31.39359090909089}, "percentage_flagged_solutions": {"bandpass": 0.390625, "clock": 0.0, "faraday": 0.0, "polalign": 0.0}}, {"station": "RS305HBA", "removed": "no", "percentage_flagged": {"initial": 6.139369523809522, "final": 37.30680346320347}, "percentage_flagged_solutions": {"bandpass": 0.390625, "clock": 0.0, "faraday": 0.0, "polalign": 0.0}}, {"station": "RS306HBA", "removed": "no", "percentage_flagged": {"initial": 6.183091601731598, "final": 23.512245021645015}, "percentage_flagged_solutions": {"bandpass": 0.390625, "clock": 0.0, "faraday": 0.0, "polalign": 0.0}}, {"station": "RS307HBA", "removed": "no", "percentage_flagged": {"initial": 6.191627012987009, "final": 27.742096536796524}, "percentage_flagged_solutions": {"bandpass": 0.390625, "clock": 0.0, "faraday": 0.0, "polalign": 0.0}}, {"station": "RS310HBA", "removed": "no", "percentage_flagged": {"initial": 6.072693376623373, "final": 31.78349004329004}, "percentage_flagged_solutions": {"bandpass": 0.390625, "clock": 0.0, "faraday": 0.0, "polalign": 0.0}}, {"station": "RS406HBA", "removed": "no", "percentage_flagged": {"initial": 6.101310779220781, "final": 28.185948051948053}, "percentage_flagged_solutions": {"bandpass": 0.390625, "clock": 0.0, "faraday": 0.0, "polalign": 0.0}}, {"station": "RS407HBA", "removed": "no", "percentage_flagged": {"initial": 6.093814848484847, "final": 26.120533766233745}, "percentage_flagged_solutions": {"bandpass": 0.390625, "clock": 0.0, "faraday": 0.0, "polalign": 0.0}}, {"station": "RS409HBA", "removed": "no", "percentage_flagged": {"initial": 6.060787619047617, "final": 31.14451385281386}, "percentage_flagged_solutions": {"bandpass": 0.390625, "clock": 0.0, "faraday": 0.0, "polalign": 0.0}}, {"station": "RS503HBA", "removed": "no", "percentage_flagged": {"initial": 6.148464242424239, "final": 25.127674458874466}, "percentage_flagged_solutions": {"bandpass": 0.390625, "clock": 0.0, "faraday": 0.0, "polalign": 0.0}}, {"station": "RS508HBA", "removed": "no", "percentage_flagged": {"initial": 6.199707878787876, "final": 32.89885844155841}, "percentage_flagged_solutions": {"bandpass": 0.390625, "clock": 0.0, "faraday": 0.0, "polalign": 0.0}}, {"station": "RS509HBA", "removed": "no", "percentage_flagged": {"initial": 6.146295238095236, "final": 30.960282683982715}, "percentage_flagged_solutions": {"bandpass": 0.390625, "clock": 0.0, "faraday": 0.0, "polalign": 0.0}}, {"station": "SE607HBA", "removed": "no", "percentage_flagged": {"initial": 100.0, "final": 100.0}, "percentage_flagged_solutions": {"bandpass": 100.0, "clock": 100.0, "faraday": 8.0078125, "polalign": 0.0}}, {"station": "UK608HBA", "removed": "no", "percentage_flagged": {"initial": 6.717805411255408, "final": 100.0}, "percentage_flagged_solutions": {"bandpass": 100.0, "clock": 100.0, "faraday": 100.0, "polalign": 0.0}}], "field_name": "3c48", "filtered_baselines_by_user": "*&", "close_sources": []}}}